lsst/__init__.py
lsst/pipe/__init__.py
lsst/pipe/base/__init__.py
lsst/pipe/base/_datasetQueryConstraints.py
lsst/pipe/base/_dataset_handle.py
lsst/pipe/base/_instrument.py
lsst/pipe/base/_observation_dimension_packer.py
lsst/pipe/base/_quantumContext.py
lsst/pipe/base/_status.py
lsst/pipe/base/_task_metadata.py
lsst/pipe/base/all_dimensions_quantum_graph_builder.py
lsst/pipe/base/automatic_connection_constants.py
lsst/pipe/base/caching_limited_butler.py
lsst/pipe/base/config.py
lsst/pipe/base/configOverrides.py
lsst/pipe/base/connectionTypes.py
lsst/pipe/base/connections.py
lsst/pipe/base/dot_tools.py
lsst/pipe/base/exec_fixup_data_id.py
lsst/pipe/base/execution_graph_fixup.py
lsst/pipe/base/execution_reports.py
lsst/pipe/base/graph_walker.py
lsst/pipe/base/log_capture.py
lsst/pipe/base/log_on_close.py
lsst/pipe/base/mermaid_tools.py
lsst/pipe/base/mp_graph_executor.py
lsst/pipe/base/pipeline.py
lsst/pipe/base/pipelineIR.py
lsst/pipe/base/pipelineTask.py
lsst/pipe/base/prerequisite_helpers.py
lsst/pipe/base/py.typed
lsst/pipe/base/quantum_graph_builder.py
lsst/pipe/base/quantum_graph_executor.py
lsst/pipe/base/quantum_graph_skeleton.py
lsst/pipe/base/quantum_provenance_graph.py
lsst/pipe/base/quantum_reports.py
lsst/pipe/base/resource_usage.py
lsst/pipe/base/separable_pipeline_executor.py
lsst/pipe/base/simple_pipeline_executor.py
lsst/pipe/base/single_quantum_executor.py
lsst/pipe/base/struct.py
lsst/pipe/base/task.py
lsst/pipe/base/taskFactory.py
lsst/pipe/base/testUtils.py
lsst/pipe/base/utils.py
lsst/pipe/base/version.py
lsst/pipe/base/cli/__init__.py
lsst/pipe/base/cli/_get_cli_subcommands.py
lsst/pipe/base/cli/cmd/__init__.py
lsst/pipe/base/cli/cmd/commands.py
lsst/pipe/base/cli/opt/__init__.py
lsst/pipe/base/cli/opt/arguments.py
lsst/pipe/base/cli/opt/options.py
lsst/pipe/base/formatters/__init__.py
lsst/pipe/base/formatters/pexConfig.py
lsst/pipe/base/graph/__init__.py
lsst/pipe/base/graph/_implDetails.py
lsst/pipe/base/graph/_loadHelpers.py
lsst_pipe_base-30.2026.400.dist-info/licenses/COPYRIGHT
lsst_pipe_base-30.2026.400.dist-info/licenses/LICENSE
lsst_pipe_base-30.2026.400.dist-info/licenses/bsd_license.txt
lsst_pipe_base-30.2026.400.dist-info/licenses/gpl-v3.0.txt
lsst_pipe_base-30.2026.400.dist-info/METADATA
lsst_pipe_base-30.2026.400.dist-info/WHEEL
lsst_pipe_base-30.2026.400.dist-info/entry_points.txt
lsst_pipe_base-30.2026.400.dist-info/top_level.txt
lsst_pipe_base-30.2026.400.dist-info/zip-safe
lsst_pipe_base-30.2026.400.dist-info/RECORD
