Metadata-Version: 2.4
Name: lsst-pipe-base
Version: 30.2026.400
Summary: Pipeline infrastructure for the Rubin Science Pipelines.
Author-email: Rubin Observatory Data Management <dm-admin@lists.lsst.org>
License-Expression: BSD-3-Clause OR GPL-3.0-or-later
Project-URL: Homepage, https://github.com/lsst/pipe_base
Project-URL: Source, https://github.com/lsst/pipe_base
Keywords: lsst
Classifier: Intended Audience :: Science/Research
Classifier: Operating System :: OS Independent
Classifier: Programming Language :: Python :: 3
Classifier: Programming Language :: Python :: 3.11
Classifier: Programming Language :: Python :: 3.12
Classifier: Programming Language :: Python :: 3.13
Classifier: Programming Language :: Python :: 3.14
Classifier: Topic :: Scientific/Engineering :: Astronomy
Requires-Python: >=3.11.0
License-File: COPYRIGHT
License-File: LICENSE
License-File: bsd_license.txt
License-File: gpl-v3.0.txt
Requires-Dist: lsst-resources[s3]
Requires-Dist: lsst-utils
Requires-Dist: lsst-daf-butler
Requires-Dist: lsst-pex-config
Requires-Dist: astropy
Requires-Dist: pydantic<3.0,>=2
Requires-Dist: networkx
Requires-Dist: wcwidth
Requires-Dist: pyyaml>=5.1
Requires-Dist: numpy>=1.17
Requires-Dist: frozendict
Requires-Dist: zstandard<0.24,>=0.23.0
Provides-Extra: test
Requires-Dist: pytest>=3.2; extra == "test"
Provides-Extra: mermaid
Requires-Dist: mermaid-py>=0.7.1; extra == "mermaid"
Dynamic: license-file
